{
  "Rooms": [
    {
      "id": 0,
      "name": "101",
      "type": "singola",
      "tags": []
    },
    {
      "id": 1,
      "name": "102",
      "type": "doppia",
      "tags": []
    },
    {
      "id": 2,
      "name": "103",
      "type": "matrimoniale",
      "tags": []
    },
    {
      "id": 3,
      "name": "104",
      "type": "tripla",
      "tags": []
    },
    {
      "id": 4,
      "name": "105",
      "type": "doppia",
      "tags": []
    },
    {
      "id": 5,
      "name": "106",
      "type": "doppia",
      "tags": []
    },
    {
      "id": 6,
      "name": "107",
      "type": "doppia",
      "tags": []
    },
    {
      "id": 7,
      "name": "108",
      "type": "doppia",
      "tags": []
    },
    {
      "id": 8,
      "name": "109",
      "type": "doppia",
      "tags": []
    },
    {
      "id": 9,
      "name": "110",
      "type": "doppia",
      "tags": []
    },
    {
      "id": 10,
      "name": "111",
      "type": "doppia",
      "tags": []
    },
    {
      "id": 11,
      "name": "112",
      "type": "doppia",
      "tags": []
    },
    {
      "id": 12,
      "name": "113",
      "type": "doppia",
      "tags": []
    },
    {
      "id": 13,
      "name": "114",
      "type": "doppia",
      "tags": []
    },
    {
      "id": 14,
      "name": "115",
      "type": "doppia",
      "tags": []
    },
    {
      "id": 15,
      "name": "116",
      "type": "doppia",
      "tags": []
    },
    {
      "id": 16,
      "name": "117",
      "type": "doppia",
      "tags": []
    },
    {
      "id": 17,
      "name": "118",
      "type": "doppia",
      "tags": []
    },
    {
      "id": 18,
      "name": "119",
      "type": "doppia",
      "tags": []
    },
    {
      "id": 19,
      "name": "120",
      "type": "doppia",
      "tags": []
    },
    {
      "id": 20,
      "name": "121",
      "type": "doppia",
      "tags": []
    },
    {
      "id": 21,
      "name": "122",
      "type": "doppia",
      "tags": []
    },
    {
      "id": 22,
      "name": "123",
      "type": "doppia",
      "tags": []
    },
    {
      "id": 23,
      "name": "123",
      "type": "matrimoniale",
      "tags": []
    },
    {
      "id": 24,
      "name": "124",
      "type": "doppia",
      "tags": []
    },
    {
      "id": 25,
      "name": "125",
      "type": "doppia",
      "tags": []
    },
    {
      "id": 26,
      "name": "126",
      "type": "doppia",
      "tags": []
    },
    {
      "id": 27,
      "name": "127",
      "type": "doppia",
      "tags": []
    }
  ],
  "Customers": [
    {
      "id": 0,
      "roomName": "101",
      "name": "adfsdfsd",
      "surname": "fsdfsdfsdf",
      "startDate": "2020-09-07",
      "endDate": "2020-09-12",
      "services": [
        "Mezza Pensione"
      ],
      "total": "45€"
    },
    {
      "id": 1,
      "roomName": "103",
      "name": "ASDASDAS",
      "surname": "DASDASDASD",
      "startDate": "2020-09-10",
      "endDate": "2020-09-17",
      "services": [
        "Pensione Completa"
      ],
      "total": "55€"
    },
    {
      "id": 2,
      "roomName": "103",
      "name": "kiiki",
      "surname": "ikikikikik",
      "startDate": "2020-09-11",
      "endDate": "2020-11-19",
      "services": [
        "Pensione Completa"
      ],
      "total": "55€"
    },
    {
      "id": 3,
      "roomName": "104",
      "name": "okookokokok",
      "surname": "llolololololololo",
      "startDate": "2020-09-01",
      "endDate": "2020-09-04",
      "services": [
        "Pensione Completa"
      ],
      "total": "55€"
    },
    {
      "id": 4,
      "roomName": "106",
      "name": "asdasdasd",
      "surname": "asdasdasd",
      "startDate": "2020-11-18",
      "endDate": "2020-11-23",
      "services": [
        "Mezza Pensione",
        "Pensione Completa"
      ],
      "total": "55€"
    },
    {
      "id": 5,
      "roomName": "106",
      "name": "dsfsd",
      "surname": "fsdfsdf",
      "startDate": "2020-09-01",
      "endDate": "2020-09-05",
      "services": [
        "Mezza Pensione"
      ],
      "total": "45€"
    },
    {
      "id": 6,
      "roomName": "106",
      "name": "sdfsdfsdfsdf",
      "surname": "sdfsdfsdfsdfsdf",
      "startDate": "2020-09-26",
      "endDate": "2020-10-13",
      "services": [
        "Pensione Completa"
      ],
      "total": "55€"
    },
    {
      "id": 7,
      "roomName": "106",
      "name": "okokokokko",
      "surname": "kokokokokkok",
      "startDate": "2020-09-17",
      "endDate": "2020-10-30",
      "services": [
        "Mezza Pensione",
        "Pensione Completa"
      ],
      "total": "100€"
    },
    {
      "id": 8,
      "roomName": "108",
      "name": "asdasdasd",
      "surname": "asdasdasdasdasd",
      "startDate": "2021-01-05",
      "endDate": "2021-01-05",
      "services": [
        "Mezza Pensione"
      ],
      "total": "45€"
    },
    {
      "id": 9,
      "roomName": "103",
      "name": "asdasd",
      "surname": "sdafasdfsdfsdf",
      "startDate": "2020-11-20",
      "endDate": "2020-11-26",
      "services": [
        "Pensione Completa"
      ],
      "total": "55€"
    }
  ],
  "Services": [
    {
      "id": 0,
      "name": "Mezza Pensione",
      "price": "45€"
    },
    {
      "id": 1,
      "name": "Pensione Completa",
      "price": "55€"
    }
  ],
  "Tags": [
    {
      "name": "Manutenzione",
      "icon": "exclamation"
    },
    {
      "name": "Da Pulire",
      "icon": "broom"
    }
  ]
}